neurobeam/__init__.py
neurobeam/__main__.py
neurobeam/configs.py
neurobeam/controller.py
neurobeam/create.py
neurobeam/data.py
neurobeam/exceptions.py
neurobeam/extensions.py
neurobeam/factories.py
neurobeam/injection.py
neurobeam/main.py
neurobeam/meta.py
neurobeam/registries.py
neurobeam/requests.py
neurobeam/timing.py
neurobeam/adapters/__init__.py
neurobeam/adapters/analog_pulse.py
neurobeam/adapters/audio_stimulus.py
neurobeam/adapters/digital_trigger.py
neurobeam/adapters/linear_actuator.py
neurobeam/adapters/stimulus_trigger.py
neurobeam/behavior/__init__.py
neurobeam/behavior/behavior.py
neurobeam/behavior/machine.py
neurobeam/behavior/states.py
neurobeam/behavior/transitions.py
neurobeam/callbacks/__init__.py
neurobeam/callbacks/console.py
neurobeam/callbacks/debug.py
neurobeam/callbacks/web.py
neurobeam/hardware/__init__.py
neurobeam/hardware/camera.py
neurobeam/hardware/daq.py
neurobeam/hardware/microscope.py
neurobeam/hardware/slm.py
neurobeam/hardware/speaker.py
neurobeam/static/MyriadPro-Regular.ttf
neurobeam/static/__init__.py
neurobeam/static/default_viewer_configuration.ini
neurobeam/static/large_logo.ico
neurobeam/static/small_logo.ico
neurobeam/static/viewer_settings.ini
neurobeam/tools/__init__.py
neurobeam/tools/audio.py
neurobeam/tools/color_scheme.py
neurobeam/tools/conditional_dispatch.py
neurobeam/tools/counter.py
neurobeam/tools/devices.py
neurobeam/tools/pattern_matching.py
neurobeam/tools/readability.py
neurobeam/tools/shuffling.py
neurobeam/tools/validators.py
neurobeam-0.3.0.dist-info/LICENSE
neurobeam-0.3.0.dist-info/METADATA
neurobeam-0.3.0.dist-info/WHEEL
neurobeam-0.3.0.dist-info/entry_points.txt
neurobeam-0.3.0.dist-info/top_level.txt
neurobeam-0.3.0.dist-info/RECORD
