Metadata-Version: 2.1
Name: neurobeam
Version: 0.3.0
Summary: Neuroscience Experiments Using Real-time Optogenetics, Behavior, and Microscopy
Author: Darik A. O'Neil
Maintainer: Darik A. O'Neil
License: MIT License
Project-URL: documentation, https://readthedocs.org
Project-URL: repository, https://github.com/darikoneil/LickSuppression
Keywords: Brain Computer Interface,BCI,Optical Brain Computer Interface,Behavior,Neuroscience,Psychology,Head-fixed,Immobile,Imaging,In-Vivo,Calcium Imaging,Two-Photon,Microscopy,Optogenetics,Holographic Optogenetics,Precision Optogenetics,Patterned Photostimulation,Fear Conditioning,Trace Fear Conditioning,Startle,Paired Pulse Inhibition,Locomotion,Closed-Loop,Real-Time,Spatial Light Modulator
Classifier: Development Status :: 2 - Pre-Alpha
Classifier: Programming Language :: Python
Classifier: Programming Language :: Python :: 3.10
Classifier: Programming Language :: C++
Classifier: Operating System :: Microsoft :: Windows
Classifier: Natural Language :: English
Classifier: License :: OSI Approved :: MIT License
Classifier: Intended Audience :: Science/Research
Classifier: Intended Audience :: End Users/Desktop
Classifier: Topic :: Scientific/Engineering
Requires-Python: <4,>=3.10
License-File: LICENSE
Requires-Dist: click
Requires-Dist: dearpygui
Requires-Dist: frozendict
Requires-Dist: importlib-metadata
Requires-Dist: memoization
Requires-Dist: nanobind
Requires-Dist: nidaqmx
Requires-Dist: numpy
Requires-Dist: opencv-python
Requires-Dist: pandas
Requires-Dist: psychtoolbox
Requires-Dist: pyarrow
Requires-Dist: pydantic
Requires-Dist: slmsuite
Requires-Dist: tomli
Requires-Dist: tomli-w
Requires-Dist: winsdk
Provides-Extra: development
Requires-Dist: boltons ; extra == 'development'
Requires-Dist: build ; extra == 'development'
Requires-Dist: coverage[toml] ; extra == 'development'
Requires-Dist: coveralls ; extra == 'development'
Requires-Dist: flake8 ; extra == 'development'
Requires-Dist: flake8-annotations ; extra == 'development'
Requires-Dist: flake8-bugbear ; extra == 'development'
Requires-Dist: flake8-class-attributes-order ; extra == 'development'
Requires-Dist: flake8-comprehensions ; extra == 'development'
Requires-Dist: flake8-html ; extra == 'development'
Requires-Dist: flake8-unused-arguments ; extra == 'development'
Requires-Dist: icecream ; extra == 'development'
Requires-Dist: tomli ; extra == 'development'
Requires-Dist: twine ; extra == 'development'
Provides-Extra: documentation
Requires-Dist: sphinx ; extra == 'documentation'
Requires-Dist: sphinx-rtd-theme ; extra == 'documentation'
Requires-Dist: sphinx-autodoc-typehints ; extra == 'documentation'
Provides-Extra: tests
Requires-Dist: pytest ; extra == 'tests'
Requires-Dist: pytest-lazy-fixture ; extra == 'tests'
Requires-Dist: pytest-sugar ; extra == 'tests'
Requires-Dist: pytest-clarity ; extra == 'tests'
Requires-Dist: pytest-timeout ; extra == 'tests'
